{
  "event_pitch": "Come on down and finally put a face to that voice! While you're here, come and join seminar or get your QSL cards checked. Not on the air yet? Then join a VE testing session, check out some radio gear, or see if lady luck is on your side at the raffle.",
  "event_flyer_text": "Please click here for the official flyer.",
  "event_flyer_path": "/uploads/copafest_2021_flyer.jpg",
  "raffle_prizes": [
    {
      "name": "Xiegu G90 SDR 20W HF",
      "image_path": "/imgs/prizes/prize_1.jpg"
    },
    {
      "name": "Icom IC-2730 Dual Band D-Star Mobile",
      "image_path": "/imgs/prizes/prize_2.jpg"
    },
    {
      "name": "Yaesu FT-70DR Dual Band Fusion",
      "image_path": "/imgs/prizes/prize_3.jpg"
    }
  ]
}
